ALU/alu.v
module alu #(
    parameter WIDTH = 8
)(
    input  [WIDTH-1:0] A,
    input  [WIDTH-1:0] B,
    input  [3:0] opcode,

    output reg [WIDTH-1:0] result,
    output reg carry,
    output reg overflow,
    output reg zero,
    output reg negative
);
    localparam OP_ADD = 4'b0000;
    localparam OP_SUB = 4'b0001;
    localparam OP_AND = 4'b0010;
    localparam OP_OR  = 4'b0011;
    localparam OP_XOR = 4'b0100;
    localparam OP_NOT = 4'b0101;
    localparam OP_SLL = 4'b0110;
    localparam OP_SRL = 4'b0111;
    localparam OP_EQ  = 4'b1000;

     reg [WIDTH:0] sum_ext;

     reg [WIDTH-1:0] and_res;
     reg [WIDTH-1:0] or_res;
     reg [WIDTH-1:0] xor_res;
     reg [WIDTH-1:0] not_res;

     reg [WIDTH-1:0] sll_res;
     reg [WIDTH-1:0] srl_res;

     reg [WIDTH-1:0] eq_res;

     always @(*) begin
         result   = 0;
         carry    = 0;
         overflow = 0;
         zero     = 0;
         negative = 0;

         sum_ext  = 0;

         and_res  = A & B;
         or_res   = A | B;
         xor_res  = A ^ B;
         not_res  = ~A;

         sll_res  = A << B[4:0];
         srl_res  = A >> B[4:0];

         eq_res   = (A == B) ? 32'd1 : 32'd0;

         case(opcode) 
             OP_ADD: begin

                 sum_ext = A + B;

                 result = sum_ext[WIDTH-1:0];

                 carry = sum_ext[WIDTH];

                 overflow =
                     (~A[WIDTH-1] & ~B[WIDTH-1] & result[WIDTH-1]) |
                     ( A[WIDTH-1] &  B[WIDTH-1] & ~result[WIDTH-1]);

             end
             OP_SUB: begin

                 sum_ext = A + (~B) + 1'b1;

                 result = sum_ext[WIDTH-1:0];

                 carry = sum_ext[WIDTH];

                 overflow =
                     (~A[WIDTH-1] &  B[WIDTH-1] & result[WIDTH-1]) |
                     ( A[WIDTH-1] & ~B[WIDTH-1] & ~result[WIDTH-1]);

             end
             OP_AND: begin
                 result = and_res;
             end
             OP_OR: begin
                 result = or_res;
             end
             OP_XOR: begin
                 result = xor_res;
             end
             OP_NOT: begin
                 result = not_res;
             end
             OP_SLL: begin
                 result = sll_res;
             end
             OP_SRL: begin
                 result = srl_res;
             end
             OP_EQ: begin
                 result = eq_res;
             end
             default: begin
                 result = 0;
             end
         
         endcase

         zero = (result == 0);

         negative = result[WIDTH-1];
     end
endmodule

Register_File/register_file2.v
`timescale 1ns/1ps
module register_file2 #(
    parameter WIDTH = 8,
    parameter DEPTH =8,
    parameter ADDRESS_WID = $clog2(DEPTH)
)(
    input clk,
    input reset,
    input we,
    input [WIDTH-1:0] w_data,
    input [ADDRESS_WID-1:0] w_address,
    input [ADDRESS_WID-1:0] r1_address,
    input [ADDRESS_WID-1:0] r2_address,

    output reg [WIDTH-1:0] r1_data,
    output reg [WIDTH-1:0] r2_data
);
    reg[WIDTH-1:0]register[0:DEPTH-1];
    
    integer i;

    

    
    always@(posedge clk) begin

	   /* $display("time=%0t reset=%b we=%b waddr=%0d",
             $time, reset, we, w_address);*/

        //reset logic
        if(reset)begin

	       // $display("%0t : RESET EXECUTED", $time);

            for(i=0; i<DEPTH; i=i+1) begin
                register[i] <= {WIDTH{1'b0}};
            end

            r1_data <= {WIDTH{1'b0}};
            r2_data <= {WIDTH{1'b0}};
	    
    	    
        end

        else begin
            //write logic
            if(we && w_address != 0)begin
                register[w_address] <= w_data;
            end

            //read logic-1
            if(r1_address == 0)begin
                r1_data <= {WIDTH{1'b0}};
            end

            else if ((r1_address == w_address) && (r1_address != 0) && we)begin
                r1_data <= w_data;
            end

            else begin
                r1_data <= register[r1_address];
            end

            //read logic-2
            if(r2_address == 0)begin
                r2_data <= {WIDTH{1'b0}};
            end

            else if ((r2_address == w_address) && (r2_address != 0) && we)begin
                r2_data <= w_data;
            end

            else begin
                r2_data <= register[r2_address];
            end
        end
    



    end
endmodule

ALU_RegisterFile/alu_rf_top.v
`timescale 1ns/1ps
module alu_rf_top #(
    parameter WIDTH = 8,
    parameter DEPTH = 8,
    parameter ADDRESS_WID = $clog2(DEPTH))

   (input clk,
    input reset,

    input [ADDRESS_WID-1:0] rs1,
    input [ADDRESS_WID-1:0] rs2,
    input [ADDRESS_WID-1:0] rd,

    input we,

    input load_mode,
    input[WIDTH-1:0] load_data,

    input [3:0]alu_code,

    output carry,
    output overflow,
    output negative,
    output zero,

    output [WIDTH-1:0]op_a_debug,
    output [WIDTH-1:0]op_b_debug,
    output [WIDTH-1:0]alu_result_debug); 
    

    wire [WIDTH-1:0]op_a;
    wire [WIDTH-1:0]op_b;
    wire [WIDTH-1:0]alu_result;
    wire [WIDTH-1:0]rf_w_data;

    localparam ADD = 4'b0000;
    localparam SUB = 4'b0001;
    localparam AND = 4'b0010;
    localparam OR  = 4'b0011;
    localparam XOR = 4'b0100;
    localparam NOT = 4'b0101;
    localparam SLL = 4'b0110;
    localparam SRL = 4'b0111;
    localparam EQ  = 4'b1000;

    register_file2#(
        .WIDTH(WIDTH),
        .DEPTH(DEPTH)
    ) rf_inst(
        .clk(clk),
        .reset(reset),
        .we(we),
        .w_data(rf_w_data),
        .w_address(rd),
        .r1_address(rs1),
        .r2_address(rs2),
        .r1_data(op_a),
        .r2_data(op_b)
    );

    alu #(
        .WIDTH(WIDTH)
    ) alu_inst(
        .A(op_a),
        .B(op_b),
        .opcode(alu_code),
        .result(alu_result),
        .carry(carry),
        .overflow(overflow),
        .zero(zero),
        .negative(negative)
    );

    assign rf_w_data = (load_mode)? load_data:alu_result;

    assign op_a_debug = op_a;
    assign op_b_debug = op_b;
    assign alu_result_debug = alu_result;

endmodule

ALU_RegisterFile/alu_rf_top_tb.v
`timescale 1ns/1ps
module alu_rf_top_tb;
    parameter WIDTH = 8;
    parameter DEPTH = 8;
    parameter ADDRESS_WID = $clog2(DEPTH);

    reg clk;
    reg reset;

    reg [ADDRESS_WID-1:0] rs1;
    reg [ADDRESS_WID-1:0] rs2;
    reg [ADDRESS_WID-1:0] rd;

    reg we;

    reg load_mode;
    reg [WIDTH-1:0] load_data;

    reg [3:0] alu_code;

    wire carry;
    wire overflow;
    wire negative;
    wire zero;

    /*Since your register file read ports are not directly visible from the testbench,
     your debug outputs become extremely valuable*/

    wire [WIDTH-1:0] op_a_debug;
    wire [WIDTH-1:0] op_b_debug;
    wire [WIDTH-1:0] alu_result_debug;

    localparam ADD = 4'b0000;
    localparam SUB = 4'b0001;
    localparam AND = 4'b0010;
    localparam OR  = 4'b0011;
    localparam XOR = 4'b0100;
    localparam NOT = 4'b0101;
    localparam SLL = 4'b0110;
    localparam SRL = 4'b0111;
    localparam EQ  = 4'b1000;
    

    alu_rf_top #(
        .WIDTH(WIDTH),
        .DEPTH(DEPTH)
    ) dut(
        .clk(clk),
        .reset(reset),
        .rs1(rs1),
        .rs2(rs2),
        .rd(rd),
        .we(we),
        .load_mode(load_mode),
        .load_data(load_data),
        .alu_code(alu_code),
        .carry(carry),
        .overflow(overflow),
        .negative(negative),
        .zero(zero),
        .op_a_debug(op_a_debug),
        .op_b_debug(op_b_debug),
        .alu_result_debug(alu_result_debug)
    );

    always #5 clk = ~clk;
    initial begin

        $dumpfile("alu_rf_top.vcd");
        $dumpvars(0,alu_rf_top_tb);

        clk = 0;
        reset = 0;
        rs1 = 0 ;
        rs2 = 0;
        rd = 0;
        we = 0;
        load_mode = 0;
        load_data = 0;
        alu_code = 0;

        //test-1
        $display("reset starting");
        reset =1;
        @(posedge clk);
        @(posedge clk);
        reset = 0;
        $display("rest done");

        //test-2
        load_mode = 1;
        we = 1;
        rd = 1;
        load_data = 10;
        @(posedge clk);
        @(negedge clk);
        we = 0;
        rs1 = 1;
        @(posedge clk);
        #2
        $display("r1 = %0d(expected = 10)",op_a_debug);

        //test-3
        load_mode = 1;
        we = 1;
        rd = 2;
        load_data = 20;
        @(posedge clk);
        @(negedge clk);
        we =0;
        rs1 = 2;
        @(posedge clk);
        #2
        $display("r2 = %0d(expected = 20)",op_a_debug);

        //test-4
        load_mode = 0;
        we = 1;
        rs1 = 1;
        rs2 = 2;
        rd = 3;
        alu_code = ADD;
        @(posedge clk);  // read operands
        #2
        $display("r1 = %0d | r2 = %0d | r1+r2 = %0d(expected = r1 = 10 | r2 = 20 | r1+r2 = 30)",op_a_debug,op_b_debug, alu_result_debug);
        
        
        @(posedge clk); // write r3
        @(negedge clk);
        we = 0;



        rs1 = 3;
        @(posedge clk); // read r3
        #2
        $display("r3 = %0d(expected = r3 = 30)",op_a_debug);

        //test-5
        load_mode = 0;
        we = 1;
        rs1 = 1;
        rs2 = 2;
        rd = 4;
        alu_code = SUB;
        @(posedge clk);  // read operands
        #2
        $display("r1 = %0d | r2 = %0d | r1-r2 = %0d(expected = r1 = 10 | r2 = 20 | r1-r2 = -10)",op_a_debug,op_b_debug, alu_result_debug);
        $display("negative = %0d(expected => negative =1)",negative);
        
        @(posedge clk); // write r3
        @(negedge clk);
        we = 0;



        rs1 = 4;
        @(posedge clk); // read r3
        #2
        $display("r4 = %0d(expected = r4 = -10)",op_a_debug);

        //test-6
        load_mode = 0;
        we = 1;
        rs1 = 1;
        rs2 = 1;
        rd = 5;
        alu_code = ADD;
        @(posedge clk);
        #2
        $display("r1 = %0d | r1 = %0d | r1+r1 = %0d",op_a_debug,op_b_debug,alu_result_debug);
        @(posedge clk);
        @(negedge clk);
        we = 0;
        rs1 = 5;
        @(posedge clk);
	#2
        $display("r5 = %0d",op_a_debug);



        //test-7
        load_mode = 0;
        we = 1;
        rs1 = 1;
        rs2 = 2;
        rd = 2;
        alu_code = ADD;
        @(posedge clk);
        #2
        $display("r1 = %0d | r2 = %0d | r1+r2 = %0d",op_a_debug,op_b_debug,alu_result_debug);
        @(posedge clk);
        @(negedge clk);
        we = 0;
        rs1 = 2;
        @(posedge clk);
	#2
        $display("r2 = %0d",op_a_debug);

        //test-8
        load_mode = 1;
        we = 1;
        rd = 6;
        load_data = 127;
        @(posedge clk);
        @(negedge clk);
        load_mode = 0;
        we =1;
        rs1 = 1;
        rs2 = 6;
        rd = 2;
        alu_code = ADD;
        @(posedge clk);
        #2
        $display("r1 = %0d | r6 = %0d | r1+r6 = %0d",op_a_debug,op_b_debug, alu_result_debug);
        $display("overflow = %0d",overflow);


	//test-9
        load_mode = 0;
        we = 1;
        rs1 = 1;
        rs2 = 2;
        rd = 3;
        alu_code = AND;
        @(posedge clk);
        #2
        $display("r1 = %0d | r2 = %0d | r1 & r2 = %0d",op_a_debug,op_b_debug,alu_result_debug);
        $display("zero = %0d",zero);
        @(posedge clk);
        @(negedge clk);
        we = 0;
        rs1 = 3;
        @(posedge clk);
        #2
        $display("r3 = %0d",op_a_debug);



        

        $display("Simulation Completed");

        #10;

        $finish;

    end
endmodule

ALU_RegisterFile/alu_rf_top.vcd
$date
	Fri Jun 05 18:05:24 2026
$end
$version
	Icarus Verilog
$end
$timescale
	1ps
$end
$scope module alu_rf_top_tb $end
$var wire 8 ! alu_result_debug [7:0] $end
$var wire 1 " carry $end
$var wire 1 # negative $end
$var wire 8 $ op_a_debug [7:0] $end
$var wire 8 % op_b_debug [7:0] $end
$var wire 1 & overflow $end
$var wire 1 ' zero $end
$var reg 4 ( alu_code [3:0] $end
$var reg 1 ) clk $end
$var reg 8 * load_data [7:0] $end
$var reg 1 + load_mode $end
$var reg 3 , rd [2:0] $end
$var reg 1 - reset $end
$var reg 3 . rs1 [2:0] $end
$var reg 3 / rs2 [2:0] $end
$var reg 1 0 we $end
$scope module dut $end
$var wire 4 1 alu_code [3:0] $end
$var wire 8 2 alu_result [7:0] $end
$var wire 8 3 alu_result_debug [7:0] $end
$var wire 1 " carry $end
$var wire 1 4 clk $end
$var wire 8 5 load_data [7:0] $end
$var wire 1 6 load_mode $end
$var wire 1 # negative $end
$var wire 8 7 op_a [7:0] $end
$var wire 8 8 op_a_debug [7:0] $end
$var wire 8 9 op_b [7:0] $end
$var wire 8 : op_b_debug [7:0] $end
$var wire 1 & overflow $end
$var wire 3 ; rd [2:0] $end
$var wire 1 < reset $end
$var wire 8 = rf_w_data [7:0] $end
$var wire 3 > rs1 [2:0] $end
$var wire 3 ? rs2 [2:0] $end
$var wire 1 @ we $end
$var wire 1 ' zero $end
$scope module rf_inst $end
$var wire 1 4 clk $end
$var wire 3 A r1_address [2:0] $end
$var wire 3 B r2_address [2:0] $end
$var wire 1 < reset $end
$var wire 3 C w_address [2:0] $end
$var wire 8 D w_data [7:0] $end
$var wire 1 @ we $end
$var integer 32 E i [31:0] $end
$var reg 8 F r1_data [7:0] $end
$var reg 8 G r2_data [7:0] $end
$upscope $end
$scope module alu_inst $end
$var wire 8 H A [7:0] $end
$var wire 8 I B [7:0] $end
$var wire 4 J opcode [3:0] $end
$var reg 8 K and_res [7:0] $end
$var reg 1 L carry $end
$var reg 8 M eq_res [7:0] $end
$var reg 1 N negative $end
$var reg 8 O not_res [7:0] $end
$var reg 8 P or_res [7:0] $end
$var reg 1 Q overflow $end
$var reg 8 R result [7:0] $end
$var reg 8 S sll_res [7:0] $end
$var reg 8 T srl_res [7:0] $end
$var reg 9 U sum_ext [8:0] $end
$var reg 8 V xor_res [7:0] $end
$var reg 1 W zero $end
$upscope $end
$upscope $end
$upscope $end
$enddefinitions $end
#0
$dumpvars
xW
bx V
bx U
bx T
bx S
bx R
xQ
bx P
bx O
xN
b0x M
xL
bx K
b0 J
bx I
bx H
bx G
bx F
bx E
bx D
b0 C
b0 B
b0 A
0@
b0 ?
b0 >
bx =
1<
b0 ;
bx :
bx 9
bx 8
bx 7
06
b0 5
04
bx 3
bx 2
b0 1
00
b0 /
b0 .
1-
b0 ,
0+
b0 *
0)
b0 (
x'
x&
bx %
bx $
x#
x"
bx !
$end
#5000
b0 =
b0 D
b1 M
b0 T
b0 S
b11111111 O
b0 V
b0 P
b0 K
b0 U
0N
0#
1W
1'
0Q
0&
0L
0"
b0 R
b0 2
b0 !
b0 3
b0 G
b0 9
b0 I
b0 %
b0 :
b0 F
b0 7
b0 H
b0 $
b0 8
b1000 E
1)
14
#10000
0)
04
#15000
b1010 =
b1010 D
b1010 *
b1010 5
b1 ,
b1 ;
b1 C
10
1@
1+
16
0-
0<
b1000 E
1)
14
#20000
0)
04
#25000
1)
14
#30000
b1 .
b1 >
b1 A
00
0@
0)
04
#35000
b1010 R
b1010 2
b1010 !
b1010 3
b1010 U
b0 M
b1010 T
b1010 S
b11110101 O
b1010 V
b1010 P
0W
0'
b1010 F
b1010 7
b1010 H
b1010 $
b1010 8
1)
14
#37000
b10100 =
b10100 D
b10100 *
b10100 5
b10 ,
b10 ;
b10 C
10
1@
#40000
0)
04
#45000
1)
14
#50000
b10 .
b10 >
b10 A
00
0@
0)
04
#55000
b10100 T
b10100 S
b11101011 O
b10100 V
b10100 P
b10100 U
b10100 R
b10100 2
b10100 !
b10100 3
b10100 F
b10100 7
b10100 H
b10100 $
b10100 8
1)
14
#57000
b11 ,
b11 ;
b11 C
b10 /
b10 ?
b10 B
b1 .
b1 >
b1 A
10
1@
0+
06
#60000
0)
04
#65000
b11110 =
b11110 D
b0 T
b0 S
b11110101 O
b11110 V
b11110 P
b11110 U
b11110 R
b11110 2
b11110 !
b11110 3
b10100 G
b10100 9
b10100 I
b10100 %
b10100 :
b1010 F
b1010 7
b1010 H
b1010 $
b1010 8
1)
14
#70000
0)
04
#75000
1)
14
#80000
b11 .
b11 >
b11 A
00
0@
0)
04
#85000
b110010 =
b110010 D
b11100001 O
b1010 V
b10100 K
b110010 U
b110010 R
b110010 2
b110010 !
b110010 3
b11110 F
b11110 7
b11110 H
b11110 $
b11110 8
1)
14
#87000
b1010 =
b1010 D
b1010 U
b1010 R
b1010 2
b1010 !
b1010 3
b1 (
b1 1
b1 J
b100 ,
b100 ;
b100 C
b1 .
b1 >
b1 A
10
1@
#90000
0)
04
#95000
b11110110 =
b11110110 D
1N
1#
1L
1"
b11110101 O
b11110 V
b0 K
b111110110 U
b11110110 R
b11110110 2
b11110110 !
b11110110 3
b1010 F
b1010 7
b1010 H
b1010 $
b1010 8
1)
14
#100000
0)
04
#105000
1)
14
#110000
b100 .
b100 >
b100 A
00
0@
0)
04
#115000
b11100010 =
b11100010 D
b1001 O
b11100010 V
b11110110 P
b10100 K
b11100010 U
1N
1#
0L
0"
b11100010 R
b11100010 2
b11100010 !
b11100010 3
b11110110 F
b11110110 7
b11110110 H
b11110110 $
b11110110 8
1)
14
#117000
b1010 =
b1010 D
1L
1"
b100001010 U
0N
0#
b1010 R
b1010 2
b1010 !
b1010 3
b0 (
b0 1
b0 J
b101 ,
b101 ;
b101 C
b1 /
b1 ?
b1 B
b1 .
b1 >
b1 A
10
1@
#120000
0)
04
#125000
b10100 =
b10100 D
b1 M
b11110101 O
b0 V
b1010 P
b1010 K
b10100 U
0L
0"
b10100 R
b10100 2
b10100 !
b10100 3
b1010 G
b1010 9
b1010 I
b1010 %
b1010 :
b1010 F
b1010 7
b1010 H
b1010 $
b1010 8
1)
14
#130000
0)
04
#135000
1)
14
#140000
b101 .
b101 >
b101 A
00
0@
0)
04
#145000
b11110 =
b11110 D
b0 M
b11101011 O
b11110 V
b11110 P
b0 K
b11110 U
b11110 R
b11110 2
b11110 !
b11110 3
b10100 F
b10100 7
b10100 H
b10100 $
b10100 8
1)
14
#147000
b10 ,
b10 ;
b10 C
b10 /
b10 ?
b10 B
b1 .
b1 >
b1 A
10
1@
#150000
0)
04
#155000
b101000 =
b101000 D
b11110101 O
b10100 V
b1010 K
b101000 U
b101000 R
b101000 2
b101000 !
b101000 3
b11110 G
b11110 9
b11110 I
b11110 %
b11110 :
b1010 F
b1010 7
b1010 H
b1010 $
b1010 8
1)
14
#160000
0)
04
#165000
b110010 =
b110010 D
b100010 V
b101010 P
b1000 K
b110010 U
b110010 R
b110010 2
b110010 !
b110010 3
b101000 G
b101000 9
b101000 I
b101000 %
b101000 :
1)
14
#170000
b10 .
b10 >
b10 A
00
0@
0)
04
#175000
b1010000 =
b1010000 D
b1 M
b11010111 O
b0 V
b101000 P
b101000 K
b1010000 U
b1010000 R
b1010000 2
b1010000 !
b1010000 3
b101000 F
b101000 7
b101000 H
b101000 $
b101000 8
1)
14
#177000
b1111111 =
b1111111 D
b1111111 *
b1111111 5
b110 ,
b110 ;
b110 C
10
1@
1+
16
#180000
0)
04
#185000
1)
14
#190000
b1010000 =
b1010000 D
b10 ,
b10 ;
b10 C
b110 /
b110 ?
b110 B
b1 .
b1 >
b1 A
0+
06
0)
04
#195000
b10001001 =
b10001001 D
1N
1#
1Q
1&
b0 M
b11110101 O
b1110101 V
b1111111 P
b1010 K
b10001001 U
b10001001 R
b10001001 2
b10001001 !
b10001001 3
b1111111 G
b1111111 9
b1111111 I
b1111111 %
b1111111 :
b1010 F
b1010 7
b1010 H
b1010 $
b1010 8
1)
14
#197000
b1010 =
b1010 D
b0 U
0N
0#
0Q
0&
b1010 R
b1010 2
b1010 !
b1010 3
b10 (
b10 1
b10 J
b11 ,
b11 ;
b11 C
b10 /
b10 ?
b10 B
#200000
0)
04
#205000
b0 =
b0 D
1W
1'
b1011010 V
b1011010 P
b0 K
b0 R
b0 2
b0 !
b0 3
b1010000 G
b1010000 9
b1010000 I
b1010000 %
b1010000 :
1)
14
#210000
0)
04
#215000
1)
14
#220000
b11 .
b11 >
b11 A
00
0@
0)
04
#225000
b11111111 O
b1010000 V
b1010000 P
1W
1'
b0 F
b0 7
b0 H
b0 $
b0 8
1)
14
