ALU/alu.v
module alu #(
    parameter WIDTH = 8
)(
    input  [WIDTH-1:0] A,
    input  [WIDTH-1:0] B,
    input  [3:0] opcode,

    output reg [WIDTH-1:0] result,
    output reg carry,
    output reg overflow,
    output reg zero,
    output reg negative
);
    localparam OP_ADD = 4'b0000;
    localparam OP_SUB = 4'b0001;
    localparam OP_AND = 4'b0010;
    localparam OP_OR  = 4'b0011;
    localparam OP_XOR = 4'b0100;
    localparam OP_NOT = 4'b0101;
    localparam OP_SLL = 4'b0110;
    localparam OP_SRL = 4'b0111;
    localparam OP_EQ  = 4'b1000;

     reg [WIDTH:0] sum_ext;

     reg [WIDTH-1:0] and_res;
     reg [WIDTH-1:0] or_res;
     reg [WIDTH-1:0] xor_res;
     reg [WIDTH-1:0] not_res;

     reg [WIDTH-1:0] sll_res;
     reg [WIDTH-1:0] srl_res;

     reg [WIDTH-1:0] eq_res;

     always @(*) begin
         result   = 0;
         carry    = 0;
         overflow = 0;
         zero     = 0;
         negative = 0;

         sum_ext  = 0;

         and_res  = A & B;
         or_res   = A | B;
         xor_res  = A ^ B;
         not_res  = ~A;

         sll_res  = A << B[4:0];
         srl_res  = A >> B[4:0];

         eq_res   = (A == B) ? 32'd1 : 32'd0;

         case(opcode) 
             OP_ADD: begin

                 sum_ext = A + B;

                 result = sum_ext[WIDTH-1:0];

                 carry = sum_ext[WIDTH];

                 overflow =
                     (~A[WIDTH-1] & ~B[WIDTH-1] & result[WIDTH-1]) |
                     ( A[WIDTH-1] &  B[WIDTH-1] & ~result[WIDTH-1]);

             end
             OP_SUB: begin

                 sum_ext = A + (~B) + 1'b1;

                 result = sum_ext[WIDTH-1:0];

                 carry = sum_ext[WIDTH];

                 overflow =
                     (~A[WIDTH-1] &  B[WIDTH-1] & result[WIDTH-1]) |
                     ( A[WIDTH-1] & ~B[WIDTH-1] & ~result[WIDTH-1]);

             end
             OP_AND: begin
                 result = and_res;
             end
             OP_OR: begin
                 result = or_res;
             end
             OP_XOR: begin
                 result = xor_res;
             end
             OP_NOT: begin
                 result = not_res;
             end
             OP_SLL: begin
                 result = sll_res;
             end
             OP_SRL: begin
                 result = srl_res;
             end
             OP_EQ: begin
                 result = eq_res;
             end
             default: begin
                 result = 0;
             end
         
         endcase

         zero = (result == 0);

         negative = result[WIDTH-1];
     end
endmodule

ALU/alu_tb.v
`timescale 1ns/1ps

module alu_tb;

    parameter WIDTH = 8;


    reg  [WIDTH-1:0] A;
    reg  [WIDTH-1:0] B;
    reg  [3:0] opcode;

    wire [WIDTH-1:0] result;
    wire carry;
    wire overflow;
    wire zero;
    wire negative;

   
    localparam OP_ADD = 4'b0000;
    localparam OP_SUB = 4'b0001;
    localparam OP_AND = 4'b0010;
    localparam OP_OR  = 4'b0011;
    localparam OP_XOR = 4'b0100;
    localparam OP_NOT = 4'b0101;
    localparam OP_SLL = 4'b0110;
    localparam OP_SRL = 4'b0111;
    localparam OP_EQ  = 4'b1000;

    
    // DUT Instantiation

    alu #(
        .WIDTH(WIDTH)
    ) dut (

        .A(A),
        .B(B),
        .opcode(opcode),

        .result(result),
        .carry(carry),
        .overflow(overflow),
        .zero(zero),
        .negative(negative)

    );

    
    // Test Sequence
    

    initial begin

        
        // Waveform Dump
        

        $dumpfile("alu.vcd");
        $dumpvars(0, alu_tb);

        

        A = 0;
        B = 0;
        opcode = 0;

        #10;

        
        // ADD Test

        A = 32'd10;
        B = 32'd5;
        opcode = OP_ADD;

        #10;

        
        // ADD Overflow Test

        A = 32'h7FFFFFFF;
        B = 32'd1;
        opcode = OP_ADD;

        #10;

        
        // SUB Test

        A = 32'd20;
        B = 32'd8;
        opcode = OP_SUB;

        #10;

        
        // AND Test
        A = 32'hF0F0F0F0;
        B = 32'h0F0F0F0F;
        opcode = OP_AND;

        #10;

        
        // OR Test
        
        A = 32'hF0F0F0F0;
        B = 32'h0F0F0F0F;
        opcode = OP_OR;

        #10;

        
        // XOR Test
       

        A = 32'hAAAA5555;
        B = 32'h5555AAAA;
        opcode = OP_XOR;

        #10;

        
        // NOT Test

        A = 32'h0000FFFF;
        B = 0;
        opcode = OP_NOT;

        #10;

        
        // Shift Left Logical Test
        
        A = 32'd4;
        B = 32'd2;
        opcode = OP_SLL;

        #10;

        
        // Shift Right Logical Test

        A = 32'd32;
        B = 32'd3;
        opcode = OP_SRL;

        #10;

        
        // Equality TRUE Test
        
        A = 32'd100;
        B = 32'd100;
        opcode = OP_EQ;

        #10;

        
        // Equality FALSE Test
        

        A = 32'd100;
        B = 32'd200;
        opcode = OP_EQ;

        #10;

        
        // Zero Flag Test
        
        A = 32'd5;
        B = 32'd5;
        opcode = OP_SUB;

        #10;

        
        // Negative Flag Test
        

        A = 32'd5;
        B = 32'd10;
        opcode = OP_SUB;

        #10;

        

        $finish;

    end

endmodule

ALU/alu.vcd
$date
	Wed May 27 10:18:48 2026
$end
$version
	Icarus Verilog
$end
$timescale
	1ps
$end
$scope module alu_tb $end
$var wire 1 ! carry $end
$var wire 1 " negative $end
$var wire 1 # overflow $end
$var wire 32 $ result [31:0] $end
$var wire 1 % zero $end
$var reg 32 & A [31:0] $end
$var reg 32 ' B [31:0] $end
$var reg 4 ( opcode [3:0] $end
$scope module dut $end
$var wire 32 ) A [31:0] $end
$var wire 32 * B [31:0] $end
$var wire 4 + opcode [3:0] $end
$var reg 32 , and_res [31:0] $end
$var reg 1 - carry $end
$var reg 32 . eq_res [31:0] $end
$var reg 1 / negative $end
$var reg 32 0 not_res [31:0] $end
$var reg 32 1 or_res [31:0] $end
$var reg 1 2 overflow $end
$var reg 32 3 result [31:0] $end
$var reg 32 4 sll_res [31:0] $end
$var reg 32 5 srl_res [31:0] $end
$var reg 33 6 sum_ext [32:0] $end
$var reg 32 7 xor_res [31:0] $end
$var reg 1 8 zero $end
$upscope $end
$upscope $end
$enddefinitions $end
#0
$dumpvars
18
b0 7
b0 6
b0 5
b0 4
b0 3
02
b0 1
b11111111111111111111111111111111 0
0/
b1 .
0-
b0 ,
b0 +
b0 *
b0 )
b0 (
b0 '
b0 &
1%
b0 $
0#
0"
0!
$end
#10000
b1111 3
b1111 $
b1111 6
b0 .
b101000000 4
b11111111111111111111111111110101 0
b1111 7
b1111 1
08
0%
b101 '
b101 *
b1010 &
b1010 )
#20000
1/
1"
12
1#
b111111111111111111111111111111 5
b11111111111111111111111111111110 4
b10000000000000000000000000000000 0
b1111111111111111111111111111110 7
b1111111111111111111111111111111 1
b1 ,
b10000000000000000000000000000000 6
b10000000000000000000000000000000 3
b10000000000000000000000000000000 $
b1 '
b1 *
b1111111111111111111111111111111 &
b1111111111111111111111111111111 )
#30000
b0 5
b1010000000000 4
b11111111111111111111111111101011 0
b11100 7
b11100 1
b0 ,
b1100 6
0/
0"
02
0#
b1100 3
b1100 $
b1 (
b1 +
b1000 '
b1000 *
b10100 &
b10100 )
#40000
18
1%
b11110000111100001 5
b1111000011110000000000000000000 4
b1111000011110000111100001111 0
b11111111111111111111111111111111 7
b11111111111111111111111111111111 1
b0 6
b0 3
b0 $
b10 (
b10 +
b1111000011110000111100001111 '
b1111000011110000111100001111 *
b11110000111100001111000011110000 &
b11110000111100001111000011110000 )
#50000
1/
1"
b11111111111111111111111111111111 3
b11111111111111111111111111111111 $
08
0%
b11 (
b11 +
#60000
b1010101010101010010101 5
b10101001010101010101010000000000 4
b1010101010101011010101010101010 0
1/
1"
b11111111111111111111111111111111 3
b11111111111111111111111111111111 $
b100 (
b100 +
b1010101010101011010101010101010 '
b1010101010101011010101010101010 *
b10101010101010100101010101010101 &
b10101010101010100101010101010101 )
#70000
b1111111111111111 5
b1111111111111111 4
b11111111111111110000000000000000 0
b1111111111111111 7
b1111111111111111 1
1/
1"
b11111111111111110000000000000000 3
b11111111111111110000000000000000 $
b101 (
b101 +
b0 '
b0 *
b1111111111111111 &
b1111111111111111 )
#80000
b1 5
b10000 4
b11111111111111111111111111111011 0
b110 7
b110 1
0/
0"
b10000 3
b10000 $
b110 (
b110 +
b10 '
b10 *
b100 &
b100 )
#90000
b100 5
b100000000 4
b11111111111111111111111111011111 0
b100011 7
b100011 1
b100 3
b100 $
b111 (
b111 +
b11 '
b11 *
b100000 &
b100000 )
#100000
b1 .
b110 5
b11001000000 4
b11111111111111111111111110011011 0
b0 7
b1100100 1
b1100100 ,
b1 3
b1 $
b1000 (
b1000 +
b1100100 '
b1100100 *
b1100100 &
b1100100 )
#110000
18
1%
b0 .
b0 5
b110010000000000 4
b10101100 7
b11101100 1
b1000000 ,
b0 3
b0 $
b11001000 '
b11001000 *
#120000
b1 .
b10100000 4
b11111111111111111111111111111010 0
b0 7
b101 1
b101 ,
18
1%
b1 (
b1 +
b101 '
b101 *
b101 &
b101 )
#130000
1/
1"
1-
1!
b11111111111111111111111111111011 3
b11111111111111111111111111111011 $
b111111111111111111111111111111011 6
b0 .
b1010000000000 4
b1111 7
b1111 1
b0 ,
08
0%
b1010 '
b1010 *
